mwcapture/README.md
mwcapture/__init__.py
mwcapture/libmwcapture.py
mwcapture/bin/x64/LibMWCapture.dll
mwcapture/bin/x64/avcodec-57.dll
mwcapture/bin/x64/avformat-57.dll
mwcapture/bin/x64/avutil-55.dll
mwcapture/bin/x64/mw_av_encoder.dll
mwcapture/bin/x64/mw_av_encoderd.dll
mwcapture/bin/x64/mw_mp4.dll
mwcapture/bin/x64/swresample-2.dll
mwcapture/bin/x86/LibMWCapture.dll
mwcapture/bin/x86/avcodec-57.dll
mwcapture/bin/x86/avformat-57.dll
mwcapture/bin/x86/avutil-55.dll
mwcapture/bin/x86/mw_av_encoder.dll
mwcapture/bin/x86/mw_av_encoderd.dll
mwcapture/bin/x86/mw_mp4.dll
mwcapture/bin/x86/swresample-2.dll
pymagewell/__init__.py
pymagewell/_version.py
pymagewell/conversion.py
pymagewell/exceptions.py
pymagewell/pro_capture_controller.py
pymagewell/py.typed
pymagewell/video_frame.py
pymagewell/events/__init__.py
pymagewell/events/device_events.py
pymagewell/events/event_base.py
pymagewell/events/notification.py
pymagewell/events/mock_win32api/__init__.py
pymagewell/events/mock_win32event/__init__.py
pymagewell/pro_capture_device/__init__.py
pymagewell/pro_capture_device/device_interface.py
pymagewell/pro_capture_device/device_settings.py
pymagewell/pro_capture_device/device_status.py
pymagewell/pro_capture_device/mock_pro_capture_device.py
pymagewell/pro_capture_device/pro_capture_device.py
pymagewell/pro_capture_device/pro_capture_device_impl.py
tests/__init__.py
tests/conftest.py
tests/test_capture_controller.py
tests/test_device.py
tests/test_event.py
tests/test_frame.py
pymagewell-0.2.1.dist-info/LICENSE
pymagewell-0.2.1.dist-info/METADATA
pymagewell-0.2.1.dist-info/WHEEL
pymagewell-0.2.1.dist-info/top_level.txt
pymagewell-0.2.1.dist-info/RECORD
