Metadata-Version: 2.1
Name: pymagewell
Version: 0.2.1
Summary: Python interface for Magewell ProCapture SDK
Home-page: https://github.com/KCL-BMEIS/pymagewell
Author: Christian Baker
Author-email: christian.baker@kcl.ac.uk,
License: MIT
Project-URL: Source, https://github.com/KCL-BMEIS/pymagewell
Project-URL: Tracker, https://github.com/KCL-BMEIS/pymagewell/issues
Classifier: Development Status :: 4 - Beta
Classifier: Intended Audience :: Developers
Classifier: Intended Audience :: Information Technology
Classifier: Intended Audience :: Science/Research
Classifier: License :: OSI Approved :: MIT License
Classifier: Natural Language :: English
Classifier: Operating System :: Microsoft :: Windows :: Windows 10
Classifier: Operating System :: POSIX :: Linux
Classifier: Operating System :: MacOS :: MacOS X
Classifier: Programming Language :: Python :: 3.9
Classifier: Programming Language :: Python :: 3.10
Classifier: Programming Language :: Python :: 3.11
Classifier: Programming Language :: Python :: 3.12
Classifier: Topic :: Multimedia :: Video :: Capture
Classifier: Typing :: Typed
Requires-Python: >=3.8
License-File: LICENSE
Requires-Dist: numpy >=1.23.4
Requires-Dist: opencv-python >=4.6.0
Requires-Dist: pywin32 >=303 ; platform_system == "Windows"
Provides-Extra: dev
Requires-Dist: flake8 ==6.1.0 ; extra == 'dev'
Requires-Dist: flake8-bugbear ==23.9.16 ; extra == 'dev'
Requires-Dist: black ==23.10.1 ; extra == 'dev'
Requires-Dist: mypy ==1.6.1 ; extra == 'dev'
Provides-Extra: doc
Requires-Dist: pdoc ==12.2.0 ; extra == 'doc'
Provides-Extra: test
Requires-Dist: pytest ==7.4.3 ; extra == 'test'
